commis/__init__.py
commis/color.py
commis/command.py
commis/exceptions.py
commis/labeled.py
commis/program.py
commis/version.py
commis-0.5.dist-info/LICENSE.txt
commis-0.5.dist-info/METADATA
commis-0.5.dist-info/WHEEL
commis-0.5.dist-info/top_level.txt
commis-0.5.dist-info/RECORD
