Metadata-Version: 2.1
Name: commis
Version: 0.5
Summary: Create command line applications like Django management commands.
Home-page: https://github.com/bbengfort/commis
Author: Benjamin Bengfort
Author-email: benjamin@bengfort.com
Maintainer: Benjamin Bengfort
Maintainer-email: benjamin@bengfort.com
License: Apache
Download-URL: https://github.com/bbengfort/commis/tarball/v0.5
Keywords: commis,management,command line interface,argparse
Platform: UNKNOWN
Classifier: Development Status :: 4 - Beta
Classifier: Environment :: Console
Classifier: License :: OSI Approved :: Apache Software License
Classifier: Natural Language :: English
Classifier: Operating System :: OS Independent
Classifier: Programming Language :: Python
Classifier: Programming Language :: Python :: 2.7
Requires-Dist: colorama (>=0.3.6)
